asamint/__init__.py
asamint/cmdline.py
asamint/compu.py
asamint/config.py
asamint/dcm20.g4
asamint/exceptions.py
asamint/logger.py
asamint/parserlib.py
asamint/templates.py
asamint/version.py
asamint/a2l/__init__.py
asamint/asam/__init__.py
asamint/asam/mdx.py
asamint/calibration/__init__.py
asamint/calibration/db_model.py
asamint/calibration/model.py
asamint/cdf/__init__.py
asamint/damos/__init__.py
asamint/damos/dcm_listener.py
asamint/damos/dcm_tester.py
asamint/data/dtds/cdf_v2.0.0.sl.dtd
asamint/data/dtds/cdf_v2.0.0.sl.xsd
asamint/data/dtds/harmonizedObjects.xsd
asamint/data/dtds/mdx_v1_0_0.sl.dtd
asamint/data/templates/dcm.tmpl
asamint/mdf/__init__.py
asamint/msrsw/__init__.py
asamint/scripts/__init__.py
asamint/scripts/xcp_log.py
asamint/utils/__init__.py
asamint/utils/xml.py
asamint/utils/optimize/__init__.py
asamint/utils/optimize/binpacking.py
asamint/xcp/__init__.py
asamint/xcp/reco.py
asamint-0.1.4.dist-info/AUTHORS.rst
asamint-0.1.4.dist-info/LICENSE
asamint-0.1.4.dist-info/METADATA
asamint-0.1.4.dist-info/WHEEL
asamint-0.1.4.dist-info/entry_points.txt
asamint-0.1.4.dist-info/top_level.txt
asamint-0.1.4.dist-info/RECORD
