Metadata-Version: 2.1
Name: asamint
Version: 0.1.4
Summary: Adds high-level, convenience, integration related functions for several opensource projects.
Home-page: https://github.com/christoph2/asamint
Author: Christoph Schueler
Author-email: Christoph Schueler <cpu12.gems@googlemail.com>
License: GNU GENERAL PUBLIC LICENSE
Project-URL: homepage, https://github.com/christoph2/asamint
Keywords: ASAM Autosar ECU Calibration Measurement
Platform: UNKNOWN
Classifier: Development Status :: 4 - Beta
Classifier: Intended Audience :: Developers
Classifier: Topic :: Software Development
Classifier: Topic :: Scientific/Engineering
Classifier: License :: OSI Approved :: GNU Lesser General Public License v3 or later (LGPLv3+)
Classifier: Programming Language :: Python :: 3.7
Classifier: Programming Language :: Python :: 3.8
Classifier: Programming Language :: Python :: 3.9
Classifier: Programming Language :: Python :: 3.10
Requires-Python: <4.0,>=3.5
License-File: LICENSE
License-File: AUTHORS.rst
Requires-Dist: asammdf
Requires-Dist: objutils
Requires-Dist: pya2ldb
Requires-Dist: pyxcp
Requires-Dist: babel
Requires-Dist: lz4
Requires-Dist: sortedcontainers
